LICENSE
README.md
setup.py
regmapGen/__init__.py
regmapGen/__main__.py
regmapGen/bitfield.py
regmapGen/config.py
regmapGen/enum.py
regmapGen/generators.py
regmapGen/reg.py
regmapGen/register_node.py
regmapGen/regmap.py
regmapGen/utils.py
regmapGen/xls_parser.py
regmapGen.egg-info/PKG-INFO
regmapGen.egg-info/SOURCES.txt
regmapGen.egg-info/dependency_links.txt
regmapGen.egg-info/entry_points.txt
regmapGen.egg-info/requires.txt
regmapGen.egg-info/top_level.txt
regmapGen/html/css/font.css
regmapGen/html/css/reset.css
regmapGen/html/css/style.css
regmapGen/html/font/S6u9w4BMUTPHh50XSwaPGR_p.woff2
regmapGen/html/font/S6u9w4BMUTPHh50XSwiPGQ.woff2
regmapGen/html/font/S6u9w4BMUTPHh6UVSwaPGR_p.woff2
regmapGen/html/font/S6u9w4BMUTPHh6UVSwiPGQ.woff2
regmapGen/html/font/S6uyw4BMUTPHjx4wXg.woff2
regmapGen/html/font/S6uyw4BMUTPHjxAwXjeu.woff2
regmapGen/html/img/option.svg
regmapGen/html/js/jquery.min.js
regmapGen/html/js/main.js
regmapGen/html/js/modernizr.js
regmapGen/templates/amm2lb_sv.j2
regmapGen/templates/apb2lb_sv.j2
regmapGen/templates/axil2lb_sv.j2
regmapGen/templates/c_header.j2
regmapGen/templates/cmsis_svd.j2
regmapGen/templates/html.j2
regmapGen/templates/ipxact_xml.j2
regmapGen/templates/regmap_asciidoc.j2
regmapGen/templates/regmap_md.j2
regmapGen/templates/regmap_py.j2
regmapGen/templates/regmap_rst.j2
regmapGen/templates/regmap_sv.j2
regmapGen/templates/regmap_sv_orig.j2
regmapGen/templates/spi2lb_sv.j2
regmapGen/templates/sv_header.j2
regmapGen/templates/sv_package.j2
regmapGen/templates/sv_wrapper.j2
regmapGen/templates/sv_wrapper_orig.j2
regmapGen/templates/uvm_regmodel.j2
regmapGen/templates/uvm_regmodel_blk.j2
regmapGen/templates/uvm_regmodel_reg.j2
regmapGen/templates/xls_example.xlsx