Metadata-Version: 2.1
Name: regmapGen
Version: 1.1.2
Summary: Генератор Регистровой Карты
Home-page: https://github.com/paulmsv/regmapGen
Author: paulmsv
Author-email: bobkovpg@gmail.com
License: MIT
Project-URL: Documentation, https://regmapGen.readthedocs.io
Platform: UNKNOWN
Classifier: Programming Language :: Python :: 3
Classifier: License :: OSI Approved :: MIT License
Classifier: Operating System :: OS Independent
Requires-Python: >=3.6
License-File: LICENSE
